judyz_cffi/Judy_cffi.h
judyz_cffi/__init__.py
judyz_cffi/_build.py
judyz_cffi/_common.py
judyz_cffi/_judy_cffi.py
judyz_cffi/exceptions.py
judyz_cffi/internal.py
judyz_cffi/judy1.py
judyz_cffi/judyl.py
judyz_cffi/judysl.py
judyz_cffi-0.9.0.dist-info/LICENSE
judyz_cffi-0.9.0.dist-info/METADATA
judyz_cffi-0.9.0.dist-info/WHEEL
judyz_cffi-0.9.0.dist-info/top_level.txt
judyz_cffi-0.9.0.dist-info/RECORD
