Metadata-Version: 2.1
Name: judyz-cffi
Version: 0.9.0
Summary: Python CFFI Judy wrapper
Home-page: https://github.com/botify-labs/judyz
Author: Yves Bastide
Author-email: yves@botify.com
License: Copyright 2015 Yves Bastide        
Platform: UNKNOWN
Classifier: Development Status :: 5 - Production/Stable
Classifier: Intended Audience :: Developers
Classifier: License :: OSI Approved :: MIT License
Classifier: Operating System :: POSIX
Classifier: Natural Language :: English
Classifier: Programming Language :: Python :: 3
Classifier: Programming Language :: Python :: 3.7
Classifier: Programming Language :: Python :: 3.8
Classifier: Programming Language :: Python :: 3.9
Classifier: Programming Language :: Python :: 3.10
License-File: LICENSE
Requires-Dist: cffi (>=1.0.0)
